{
"autoplayBgm":false,"autoplayBgs":false,"battleback1Name":"","battleback2Name":"","bgm":{"name":"","pan":0,"pitch":100,"volume":90},"bgs":{"name":"","pan":0,"pitch":100,"volume":90},"disableDashing":false,"displayName":"","encounterList":[],"encounterStep":30,"note":"","parallaxLoopX":false,"parallaxLoopY":false,"parallaxName":"","parallaxShow":true,"parallaxSx":0,"parallaxSy":0,"scrollType":0,"specifyBattleback":false,"height":13,"width":13,"mapId":114,"tilesetId":26,
"data":[0,0,0,0,0,0,0,0,0,0,0,0,0,0,0,0,0,0,0,0,0,0,0,0,0,0,0,0,0,0,0,0,0,0,0,0,0,0,0,0,0,0,0,0,0,0,0,0,0,0,0,0,0,0,0,0,0,0,0,0,0,0,0,0,0,0,0,0,0,0,0,0,0,0,0,0,0,0,0,0,0,0,0,0,0,0,0,0,0,0,0,0,0,0,0,0,0,0,0,0,0,0,0,0,0,0,0,0,0,0,0,0,0,0,0,0,0,0,0,0,0,0,0,0,0,0,0,0,0,0,0,0,0,0,0,0,0,0,0,0,0,0,0,0,0,0,0,0,0,0,0,0,0,0,0,0,0,0,0,0,0,0,0,0,0,0,0,0,0,0,0,0,0,0,0,0,0,0,0,0,0,0,0,0,0,0,0,0,0,0,0,0,0,0,0,0,0,0,0,0,0,0,0,0,0,0,0,0,0,0,0,0,0,0,0,0,0,0,0,0,0,0,0,0,0,0,0,0,0,0,0,0,0,0,0,0,0,0,0,0,0,0,0,0,0,0,0,0,0,0,0,0,0,0,0,0,0,0,0,0,0,0,0,0,0,0,0,0,0,0,0,0,0,0,0,0,0,0,0,0,0,0,0,0,0,0,0,0,0,0,0,0,0,0,0,0,0,0,0,0,0,0,0,0,0,0,0,0,0,0,0,0,0,0,0,0,0,0,0,0,0,0,0,0,0,0,0,0,0,0,0,0,0,0,0,0,0,0,1,1,1,1,1,1,1,1,1,1,1,1,1,1,41,30,49,152,41,14,15,136,41,30,49,1,1,49,38,57,160,49,152,41,30,49,38,57,1,1,57,58,288,272,57,160,49,38,57,58,137,1,1,290,175,296,297,264,167,57,58,178,272,272,1,1,264,264,264,264,264,272,272,272,264,264,272,1,1,272,272,272,264,272,272,272,272,272,32,33,1,1,33,34,272,264,264,264,158,32,33,6,41,1,1,41,128,33,34,129,32,33,6,41,14,15,1,1,15,136,41,128,33,6,41,14,15,136,41,1,1,41,14,15,136,41,14,15,22,41,144,15,1,1,15,22,41,14,15,22,41,144,15,136,41,1,1,1,1,1,1,1,1,1,1,1,1,1,1,0,0,0,0,0,0,0,0,0,0,0,0,0,0,0,0,0,0,0,0,0,0,0,0,0,0,0,0,0,0,0,0,0,0,0,0,0,0,0,0,0,0,0,0,0,0,0,0,0,0,0,0,0,0,0,0,0,0,0,0,0,0,0,0,0,0,0,0,0,0,0,0,0,0,0,0,0,0,0,0,0,0,0,0,0,0,0,0,0,0,0,0,0,0,0,0,0,0,0,0,0,0,0,0,0,0,0,0,0,0,0,0,0,0,0,0,0,0,0,0,0,0,0,0,0,0,0,0,0,0,0,0,0,0,0,0,0,0,0,0,0,0,0,0,0,0,0,0,0,0,0,0,0,0,0,0,0,0,0,0,0,0,0,0,0,0,0,0,0,0,0,0,0,0,0,0,0,0,0,0,0,0,0,0,0,0,0,0,0,0,0,0,0,0,0,0,0,0,0,0,0,0,0,0,0,0,0,0,0,0,0,0,0,0,0,0,0,0,0,0,0,0,0,0,0,0,0,0,0,0,0,0,0,0,0,0,0,0,0,0,0,0,0,0,0,0,0,0,0,0,0,0,0,0,0,0,0,0,0,0,0,0,0,0,0,0,0,0,0,0,0,0,0,0,0,0,0,0,0,0,0,0,0,0,0,0,0,0,0,0,0,0,0,0,0,0,0,0,0,0,0,0,0,0,0,0,0,0,0,0,0,0,0,0,0,0,0,0,0,0,0,0,0,0,0,0,0,0,0,0,0,0,0,0,0,0,0,0,0,0,0,0,0,0,0,0,0,0,0,0,0,0,1,1,1,1,1,1,1,1,1,1,1,0,0,0,0,1,0,0,0,0,0,0,0,1,0,0,1,0,0,0,1,0,0,0,1,0,0,0,0,0,0,1,0,0,0,1,0,0,0,0,0,0,0,0,0,0,0,0,0,0,0,0,0,0,0,0,0,0,0,0,0,0,0,0,0,0,0,0,0,0,0,0,0,0,0,0,0,0,0,0,0,0,0,0,0,0,0,0,0,0,0,0,0,0,0,0,0,0,0,0,0,0,0,0,1,0,0,1,0,0,0,0,0,0,0,1,0,0,0,0,0,0,1,0,0,0,1,0,0,0,1,0,0,0,0,0,0,0,0,0,0,0,0,0,0],
"events":[
null,
{"id":1,"name":"사디야","note":"","pages":[{"conditions":{"actorId":1,"actorValid":false,"itemId":1,"itemValid":false,"selfSwitchCh":"A","selfSwitchValid":false,"switch1Id":1,"switch1Valid":false,"switch2Id":1,"switch2Valid":false,"variableId":1,"variableValid":false,"variableValue":0},"directionFix":false,"image":{"tileId":0,"characterName":"$사디야보행MV90x90_270x360","direction":4,"pattern":1,"characterIndex":0},"list":[{"code":108,"indent":0,"parameters":["<shadow>"]},{"code":0,"indent":0,"parameters":[]}],"moveFrequency":3,"moveRoute":{"list":[{"code":0,"parameters":[]}],"repeat":true,"skippable":false,"wait":false},"moveSpeed":3,"moveType":0,"priorityType":1,"stepAnime":false,"through":false,"trigger":0,"walkAnime":true}],"x":8,"y":5},
{"id":2,"name":"푸산","note":"푸산","pages":[{"conditions":{"actorId":1,"actorValid":false,"itemId":1,"itemValid":false,"selfSwitchCh":"A","selfSwitchValid":false,"switch1Id":1,"switch1Valid":false,"switch2Id":1,"switch2Valid":false,"variableId":1,"variableValid":false,"variableValue":0},"directionFix":false,"image":{"tileId":0,"characterName":"$Actor8","direction":4,"pattern":1,"characterIndex":0},"list":[{"code":108,"indent":0,"parameters":["<shadow>"]},{"code":0,"indent":0,"parameters":[]}],"moveFrequency":3,"moveRoute":{"list":[{"code":0,"parameters":[]}],"repeat":true,"skippable":false,"wait":false},"moveSpeed":3,"moveType":0,"priorityType":1,"stepAnime":false,"through":false,"trigger":0,"walkAnime":true}],"x":9,"y":6},
{"id":3,"name":"지그자겔","note":"","pages":[{"conditions":{"actorId":1,"actorValid":false,"itemId":1,"itemValid":false,"selfSwitchCh":"A","selfSwitchValid":false,"switch1Id":1,"switch1Valid":false,"switch2Id":1,"switch2Valid":false,"variableId":1,"variableValid":false,"variableValue":0},"directionFix":false,"image":{"tileId":0,"characterName":"$지그자겔보행MV90x90_270x360","direction":4,"pattern":1,"characterIndex":0},"list":[{"code":108,"indent":0,"parameters":["<shadow>"]},{"code":0,"indent":0,"parameters":[]}],"moveFrequency":3,"moveRoute":{"list":[{"code":0,"parameters":[]}],"repeat":true,"skippable":false,"wait":false},"moveSpeed":3,"moveType":0,"priorityType":1,"stepAnime":false,"through":false,"trigger":0,"walkAnime":true}],"x":8,"y":6},
{"id":4,"name":"오마왕의 계략","note":"","pages":[{"conditions":{"actorId":1,"actorValid":false,"itemId":1,"itemValid":false,"selfSwitchCh":"A","selfSwitchValid":false,"switch1Id":1,"switch1Valid":false,"switch2Id":1,"switch2Valid":false,"variableId":1,"variableValid":false,"variableValue":0},"directionFix":false,"image":{"characterIndex":0,"characterName":"","direction":2,"pattern":0,"tileId":0},"list":[{"code":211,"indent":0,"parameters":[0]},{"code":241,"indent":0,"parameters":[{"name":"sadia_","volume":100,"pitch":100,"pan":0}]},{"code":222,"indent":0,"parameters":[]},{"code":205,"indent":0,"parameters":[1,{"list":[{"code":2,"indent":null},{"code":2,"indent":null},{"code":0}],"repeat":false,"skippable":false,"wait":false}]},{"code":505,"indent":0,"parameters":[{"code":2,"indent":null}]},{"code":505,"indent":0,"parameters":[{"code":2,"indent":null}]},{"code":205,"indent":0,"parameters":[3,{"list":[{"code":2,"indent":null},{"code":2,"indent":null},{"code":2,"indent":null},{"code":0}],"repeat":false,"skippable":false,"wait":false}]},{"code":505,"indent":0,"parameters":[{"code":2,"indent":null}]},{"code":505,"indent":0,"parameters":[{"code":2,"indent":null}]},{"code":505,"indent":0,"parameters":[{"code":2,"indent":null}]},{"code":205,"indent":0,"parameters":[2,{"list":[{"code":41,"parameters":["푸산%(4)",1],"indent":null},{"code":2,"indent":null},{"code":41,"parameters":["푸산%(4)",0],"indent":null},{"code":17,"indent":null},{"code":0}],"repeat":false,"skippable":false,"wait":false}]},{"code":505,"indent":0,"parameters":[{"code":41,"parameters":["푸산%(4)",1],"indent":null}]},{"code":505,"indent":0,"parameters":[{"code":2,"indent":null}]},{"code":505,"indent":0,"parameters":[{"code":41,"parameters":["푸산%(4)",0],"indent":null}]},{"code":505,"indent":0,"parameters":[{"code":17,"indent":null}]},{"code":101,"indent":0,"parameters":["",0,0,0]},{"code":401,"indent":0,"parameters":["\\pop[2]\\c[29]이봐. 정말 아마조나에 그런 숨겨진 힘이 있을까?"]},{"code":205,"indent":0,"parameters":[3,{"list":[{"code":18,"indent":null},{"code":0}],"repeat":false,"skippable":false,"wait":false}]},{"code":505,"indent":0,"parameters":[{"code":18,"indent":null}]},{"code":213,"indent":0,"parameters":[1,8,true]},{"code":205,"indent":0,"parameters":[1,{"list":[{"code":41,"parameters":["$사디야_앞_우응시",0],"indent":null},{"code":0}],"repeat":false,"skippable":false,"wait":false}]},{"code":505,"indent":0,"parameters":[{"code":41,"parameters":["$사디야_앞_우응시",0],"indent":null}]},{"code":101,"indent":0,"parameters":["",0,0,0]},{"code":401,"indent":0,"parameters":["\\pop[1]\\c[26]아마조나는 먼 옛날 비연님께서 그 곳에 터를 "]},{"code":401,"indent":0,"parameters":["잡으시면서부터 동시에 아마조나의 사람들은 어떤 신비한 "]},{"code":401,"indent":0,"parameters":["힘을 갖고 태어나게 되었어. 그 힘은 마법 따위의 힘이 아니지. "]},{"code":401,"indent":0,"parameters":["대부분 보통의 여성은 남성보다 신체적으로 약하게 타고나."]},{"code":101,"indent":0,"parameters":["",0,0,0]},{"code":401,"indent":0,"parameters":["\\pop[1]\\c[26]하지만 그런 자연의 순리를 넘어서 아마조나의 여성은 남성보다 "]},{"code":401,"indent":0,"parameters":["강인하게 태어나. 그러한 일이 어떻게 가능할지 생각해보면 알 수 있지 않겠어?"]},{"code":213,"indent":0,"parameters":[2,8,true]},{"code":101,"indent":0,"parameters":["",0,0,0]},{"code":401,"indent":0,"parameters":["\\pop[3]\\c[27]마타도 아마조나 프롬이잖아?"]},{"code":205,"indent":0,"parameters":[1,{"list":[{"code":41,"parameters":["$사디야_앞_좌응시",0],"indent":null},{"code":0}],"repeat":false,"skippable":false,"wait":false}]},{"code":505,"indent":0,"parameters":[{"code":41,"parameters":["$사디야_앞_좌응시",0],"indent":null}]},{"code":101,"indent":0,"parameters":["",0,0,0]},{"code":401,"indent":0,"parameters":["\\pop[1]\\c[26]그래. 마타도 아마조나 출신이지."]},{"code":401,"indent":0,"parameters":["그렇기 때문에 천궁에서도 마타를 선택한 거고."]},{"code":205,"indent":0,"parameters":[1,{"list":[{"code":41,"parameters":["$사디야_앞_우응시",0],"indent":null},{"code":0}],"repeat":false,"skippable":false,"wait":false}]},{"code":505,"indent":0,"parameters":[{"code":41,"parameters":["$사디야_앞_우응시",0],"indent":null}]},{"code":101,"indent":0,"parameters":["",0,0,0]},{"code":401,"indent":0,"parameters":["\\pop[2]\\c[29]그래서… …. 어머니께서 어떠한 힘을 가지고 "]},{"code":401,"indent":0,"parameters":["아마조나에 들어가셨다, 그건가?"]},{"code":101,"indent":0,"parameters":["",0,0,0]},{"code":401,"indent":0,"parameters":["\\pop[1]\\c[26]아직까지는 추측이지만. 만약 그렇다면"]},{"code":101,"indent":0,"parameters":["",0,0,0]},{"code":401,"indent":0,"parameters":["\\pop[3]\\c[27]그 파워를 잠깐 보로우 하자는거지."]},{"code":101,"indent":0,"parameters":["",0,0,0]},{"code":401,"indent":0,"parameters":["\\pop[1]\\c[26]뺏자는게 아니야. 우린 그 것을 잠깐 빌리자는거야."]},{"code":101,"indent":0,"parameters":["",0,0,0]},{"code":401,"indent":0,"parameters":["\\pop[3]\\c[27]그리고 아마조나는 프린스의 프롬이니까."]},{"code":101,"indent":0,"parameters":["",0,0,0]},{"code":401,"indent":0,"parameters":["\\pop[1]\\c[26]아마조나의 속사정을 잘 아는 너만이 이 일을 할 수 있어."]},{"code":401,"indent":0,"parameters":["그리고 반드시 그래야만 해."]},{"code":213,"indent":0,"parameters":[2,8,true]},{"code":101,"indent":0,"parameters":["",0,0,0]},{"code":401,"indent":0,"parameters":["\\pop[2]\\c[29]알겠다. 다만 아마조나는 나 혼자서 간다. "]},{"code":401,"indent":0,"parameters":["너희는 밖에서 기다리고 있어라. 또한 그들을 우연히 "]},{"code":401,"indent":0,"parameters":["마주치더라도 절대 해치지 않는다고 약속 해라."]},{"code":101,"indent":0,"parameters":["",0,0,0]},{"code":401,"indent":0,"parameters":["\\pop[1]\\c[26]좋아. 약속하지. 대신, 확실하게 가지고 와야 해."]},{"code":213,"indent":0,"parameters":[2,8,true]},{"code":230,"indent":0,"parameters":[60]},{"code":101,"indent":0,"parameters":["",0,0,0]},{"code":401,"indent":0,"parameters":["\\pop[2]\\c[29]여기서 기다려."]},{"code":201,"indent":0,"parameters":[0,760,27,24,0,0]},{"code":121,"indent":0,"parameters":[1,1,0]},{"code":121,"indent":0,"parameters":[1,1,1]},{"code":0,"indent":0,"parameters":[]}],"moveFrequency":5,"moveRoute":{"list":[{"code":0,"parameters":[]}],"repeat":true,"skippable":false,"wait":false},"moveSpeed":4,"moveType":0,"priorityType":1,"stepAnime":false,"through":false,"trigger":3,"walkAnime":true},{"conditions":{"actorId":1,"actorValid":false,"itemId":1,"itemValid":false,"selfSwitchCh":"A","selfSwitchValid":false,"switch1Id":1,"switch1Valid":true,"switch2Id":1,"switch2Valid":false,"variableId":1,"variableValid":false,"variableValue":0},"directionFix":false,"image":{"characterIndex":0,"characterName":"","direction":2,"pattern":0,"tileId":0},"list":[{"code":0,"indent":0,"parameters":[]}],"moveFrequency":3,"moveRoute":{"list":[{"code":0,"parameters":[]}],"repeat":true,"skippable":false,"wait":false},"moveSpeed":3,"moveType":0,"priorityType":0,"stepAnime":false,"through":false,"trigger":0,"walkAnime":true}],"x":3,"y":4},
{"id":5,"name":"EV005","note":"","pages":[{"conditions":{"actorId":1,"actorValid":false,"itemId":1,"itemValid":false,"selfSwitchCh":"A","selfSwitchValid":false,"switch1Id":1,"switch1Valid":false,"switch2Id":1,"switch2Valid":false,"variableId":1,"variableValid":false,"variableValue":0},"directionFix":false,"image":{"characterIndex":0,"characterName":"","direction":2,"pattern":0,"tileId":0},"list":[{"code":0,"indent":0,"parameters":[]}],"moveFrequency":3,"moveRoute":{"list":[{"code":0,"parameters":[]}],"repeat":true,"skippable":false,"wait":false},"moveSpeed":3,"moveType":0,"priorityType":1,"stepAnime":false,"through":false,"trigger":0,"walkAnime":true}],"x":6,"y":8},
{"id":6,"name":"EV006","note":"","pages":[{"conditions":{"actorId":1,"actorValid":false,"itemId":1,"itemValid":false,"selfSwitchCh":"A","selfSwitchValid":false,"switch1Id":1,"switch1Valid":false,"switch2Id":1,"switch2Valid":false,"variableId":1,"variableValid":false,"variableValue":0},"directionFix":false,"image":{"characterIndex":0,"characterName":"","direction":2,"pattern":0,"tileId":0},"list":[{"code":0,"indent":0,"parameters":[]}],"moveFrequency":3,"moveRoute":{"list":[{"code":0,"parameters":[]}],"repeat":true,"skippable":false,"wait":false},"moveSpeed":3,"moveType":0,"priorityType":1,"stepAnime":false,"through":false,"trigger":0,"walkAnime":true}],"x":4,"y":8},
{"id":7,"name":"EV007","note":"","pages":[{"conditions":{"actorId":1,"actorValid":false,"itemId":1,"itemValid":false,"selfSwitchCh":"A","selfSwitchValid":false,"switch1Id":1,"switch1Valid":false,"switch2Id":1,"switch2Valid":false,"variableId":1,"variableValid":false,"variableValue":0},"directionFix":false,"image":{"characterIndex":0,"characterName":"","direction":2,"pattern":0,"tileId":0},"list":[{"code":0,"indent":0,"parameters":[]}],"moveFrequency":3,"moveRoute":{"list":[{"code":0,"parameters":[]}],"repeat":true,"skippable":false,"wait":false},"moveSpeed":3,"moveType":0,"priorityType":1,"stepAnime":false,"through":false,"trigger":0,"walkAnime":true}],"x":5,"y":9},
{"id":8,"name":"EV008","note":"","pages":[{"conditions":{"actorId":1,"actorValid":false,"itemId":1,"itemValid":false,"selfSwitchCh":"A","selfSwitchValid":false,"switch1Id":1,"switch1Valid":false,"switch2Id":1,"switch2Valid":false,"variableId":1,"variableValid":false,"variableValue":0},"directionFix":false,"image":{"characterIndex":0,"characterName":"","direction":2,"pattern":0,"tileId":0},"list":[{"code":0,"indent":0,"parameters":[]}],"moveFrequency":3,"moveRoute":{"list":[{"code":0,"parameters":[]}],"repeat":true,"skippable":false,"wait":false},"moveSpeed":3,"moveType":0,"priorityType":1,"stepAnime":false,"through":false,"trigger":0,"walkAnime":true}],"x":5,"y":7}
]
}